<?xml version="1.0" encoding="utf-8"?>
<TextureAtlas imagePath="bfCar.png">
	<!-- Created with Adobe Animate version 19.2.1.408 -->
	<!-- http://www.adobe.com/products/animate.html -->
	<SubTexture name="BF NOTE DOWN0000" x="0" y="0" width="416" height="372" pivotX="-50.5" pivotY="-37.45" frameX="-1" frameY="-2" frameWidth="417" frameHeight="374"/>
	<SubTexture name="BF NOTE DOWN0001" x="416" y="0" width="416" height="372" frameX="-1" frameY="-2" frameWidth="417" frameHeight="374"/>
	<SubTexture name="BF NOTE DOWN0002" x="832" y="0" width="412" height="374" frameX="0" frameY="0" frameWidth="417" frameHeight="374"/>
	<SubTexture name="BF NOTE DOWN0003" x="1244" y="0" width="412" height="374" frameX="0" frameY="0" frameWidth="417" frameHeight="374"/>
	<SubTexture name="BF NOTE DOWN0004" x="1244" y="0" width="412" height="374" frameX="0" frameY="0" frameWidth="417" frameHeight="374"/>
	<SubTexture name="BF NOTE DOWN0005" x="1244" y="0" width="412" height="374" frameX="0" frameY="0" frameWidth="417" frameHeight="374"/>
	<SubTexture name="BF NOTE LEFT0000" x="0" y="1189" width="417" height="414" pivotX="-28.15" pivotY="5.4" frameX="0" frameY="0" frameWidth="418" frameHeight="414"/>
	<SubTexture name="BF NOTE LEFT0001" x="417" y="1189" width="417" height="414" frameX="0" frameY="0" frameWidth="418" frameHeight="414"/>
	<SubTexture name="BF NOTE LEFT0002" x="834" y="1189" width="411" height="414" frameX="-7" frameY="0" frameWidth="418" frameHeight="414"/>
	<SubTexture name="BF NOTE LEFT0003" x="1245" y="1189" width="411" height="414" frameX="-7" frameY="0" frameWidth="418" frameHeight="414"/>
	<SubTexture name="BF NOTE LEFT0004" x="1245" y="1189" width="411" height="414" frameX="-7" frameY="0" frameWidth="418" frameHeight="414"/>
	<SubTexture name="BF NOTE LEFT0005" x="1245" y="1189" width="411" height="414" frameX="-7" frameY="0" frameWidth="418" frameHeight="414"/>
	<SubTexture name="BF NOTE RIGHT0000" x="0" y="1603" width="446" height="407" pivotX="-27.95" pivotY="-1.2" frameX="-6" frameY="0" frameWidth="452" frameHeight="407"/>
	<SubTexture name="BF NOTE RIGHT0001" x="446" y="1603" width="446" height="407" frameX="-6" frameY="0" frameWidth="452" frameHeight="407"/>
	<SubTexture name="BF NOTE RIGHT0002" x="892" y="1603" width="450" height="407" frameX="0" frameY="0" frameWidth="452" frameHeight="407"/>
	<SubTexture name="BF NOTE RIGHT0003" x="1342" y="1603" width="450" height="407" frameX="0" frameY="0" frameWidth="452" frameHeight="407"/>
	<SubTexture name="BF NOTE RIGHT0004" x="1342" y="1603" width="450" height="407" frameX="0" frameY="0" frameWidth="452" frameHeight="407"/>
	<SubTexture name="BF NOTE RIGHT0005" x="1342" y="1603" width="450" height="407" frameX="0" frameY="0" frameWidth="452" frameHeight="407"/>
	<SubTexture name="BF NOTE RIGHT0006" x="1342" y="1603" width="450" height="407" frameX="0" frameY="0" frameWidth="452" frameHeight="407"/>
	<SubTexture name="BF NOTE UP0000" x="1815" y="0" width="419" height="451" pivotX="-67.05" pivotY="41.65" frameX="-4" frameY="-2" frameWidth="428" frameHeight="453"/>
	<SubTexture name="BF NOTE UP0001" x="1815" y="451" width="419" height="453" frameX="-4" frameY="0" frameWidth="428" frameHeight="453"/>
	<SubTexture name="BF NOTE UP0002" x="1792" y="1351" width="428" height="447" frameX="0" frameY="-6" frameWidth="428" frameHeight="453"/>
	<SubTexture name="BF NOTE UP0003" x="1792" y="1351" width="428" height="449" frameX="0" frameY="-4" frameWidth="428" frameHeight="453"/>
	<SubTexture name="BF NOTE UP0004" x="1792" y="1351" width="428" height="448" frameX="0" frameY="-5" frameWidth="428" frameHeight="453"/>
	<SubTexture name="BF NOTE UP0005" x="1792" y="1351" width="428" height="452" frameX="0" frameY="-1" frameWidth="428" frameHeight="453"/>
	<SubTexture name="BF NOTE UP0006" x="1792" y="1351" width="428" height="447" frameX="0" frameY="-6" frameWidth="428" frameHeight="453"/>
	<SubTexture name="BF NOTE UP0007" x="1792" y="1351" width="428" height="449" frameX="0" frameY="-4" frameWidth="428" frameHeight="453"/>
	<SubTexture name="BF NOTE UP0008" x="1792" y="1351" width="428" height="448" frameX="0" frameY="-5" frameWidth="428" frameHeight="453"/>
	<SubTexture name="BF NOTE UP0009" x="1792" y="1351" width="428" height="452" frameX="0" frameY="-1" frameWidth="428" frameHeight="453"/>
	<SubTexture name="BF idle dance0000" x="0" y="374" width="456" height="405" pivotX="0.35" pivotY="0" frameX="0" frameY="-4" frameWidth="456" frameHeight="409"/>
	<SubTexture name="BF idle dance0001" x="456" y="374" width="456" height="405" frameX="0" frameY="-4" frameWidth="456" frameHeight="409"/>
	<SubTexture name="BF idle dance0002" x="912" y="374" width="454" height="405" frameX="0" frameY="-4" frameWidth="456" frameHeight="409"/>
	<SubTexture name="BF idle dance0003" x="1366" y="374" width="449" height="406" frameX="0" frameY="-4" frameWidth="456" frameHeight="409"/>
	<SubTexture name="BF idle dance0004" x="0" y="780" width="449" height="408" frameX="0" frameY="-3" frameWidth="456" frameHeight="409"/>
	<SubTexture name="BF idle dance0005" x="449" y="780" width="449" height="408" frameX="0" frameY="-3" frameWidth="456" frameHeight="409"/>
	<SubTexture name="BF idle dance0006" x="449" y="780" width="449" height="408" frameX="0" frameY="-1" frameWidth="456" frameHeight="409"/>
	<SubTexture name="BF idle dance0007" x="449" y="780" width="449" height="408" frameX="0" frameY="-1" frameWidth="456" frameHeight="409"/>
	<SubTexture name="BF idle dance0008" x="449" y="780" width="449" height="408" frameX="0" frameY="0" frameWidth="456" frameHeight="409"/>
	<SubTexture name="BF idle dance0009" x="898" y="780" width="449" height="409" frameX="0" frameY="0" frameWidth="456" frameHeight="409"/>
	<SubTexture name="BF idle dance0010" x="1347" y="780" width="449" height="409" frameX="0" frameY="0" frameWidth="456" frameHeight="409"/>
	<SubTexture name="BF idle dance0011" x="1347" y="780" width="449" height="409" frameX="0" frameY="0" frameWidth="456" frameHeight="409"/>
	<SubTexture name="BF idle dance0012" x="1347" y="780" width="449" height="409" frameX="0" frameY="0" frameWidth="456" frameHeight="409"/>
	<SubTexture name="BF idle dance0013" x="898" y="780" width="449" height="409" frameX="0" frameY="0" frameWidth="456" frameHeight="409"/>
	</TextureAtlas>
